ExcelLibrary.py
robotframework_excellib_xlsm-2.0.3.dist-info/LICENSE
robotframework_excellib_xlsm-2.0.3.dist-info/METADATA
robotframework_excellib_xlsm-2.0.3.dist-info/WHEEL
robotframework_excellib_xlsm-2.0.3.dist-info/top_level.txt
robotframework_excellib_xlsm-2.0.3.dist-info/RECORD
