Metadata-Version: 2.1
Name: robotframework-excellib-xlsm
Version: 2.0.3
Summary: Robot Framework library for working with Excel documents
Home-page: https://github.com/TheOddPanda/robotframework-excellib
Author: TheOddPanda
Author-email: adrian.buechi@ergon.ch
License: Apache License 2.0
Keywords: testing testautomation robotframework excel
Platform: UNKNOWN
Classifier: Development Status :: 5 - Production/Stable
Classifier: Intended Audience :: Developers
Classifier: Topic :: Software Development :: Testing
Classifier: License :: OSI Approved :: Apache Software License
Classifier: Programming Language :: Python :: 3.5
Classifier: Programming Language :: Python :: 3.6
Classifier: Framework :: Robot Framework :: Library
Requires-Dist: openpyxl (>=3.0.4)
Requires-Dist: robotframework (>=3.2.1)
Requires-Dist: future (>=0.18.2) ; python_version <= "3.8"
